MANIFEST.in
README.md
setup.cfg
setup.py
jaidedread/__init__.py
jaidedread/craft.py
jaidedread/craft_utils.py
jaidedread/detection.py
jaidedread/imgproc.py
jaidedread/jaidedread.py
jaidedread/model.py
jaidedread/modules.py
jaidedread/recognition.py
jaidedread/utils.py
jaidedread.egg-info/PKG-INFO
jaidedread.egg-info/SOURCES.txt
jaidedread.egg-info/dependency_links.txt
jaidedread.egg-info/requires.txt
jaidedread.egg-info/top_level.txt
jaidedread/character/af_char.txt
jaidedread/character/az_char.txt
jaidedread/character/bs_char.txt
jaidedread/character/cs_char.txt
jaidedread/character/cy_char.txt
jaidedread/character/da_char.txt
jaidedread/character/de_char.txt
jaidedread/character/en_char.txt
jaidedread/character/es_char.txt
jaidedread/character/et_char.txt
jaidedread/character/fr_char.txt
jaidedread/character/ga_char.txt
jaidedread/character/hr_char.txt
jaidedread/character/hu_char.txt
jaidedread/character/id_char.txt
jaidedread/character/is_char.txt
jaidedread/character/it_char.txt
jaidedread/character/ku_char.txt
jaidedread/character/la_char.txt
jaidedread/character/lt_char.txt
jaidedread/character/lv_char.txt
jaidedread/character/mi_char.txt
jaidedread/character/ms_char.txt
jaidedread/character/mt_char.txt
jaidedread/character/nl_char.txt
jaidedread/character/no_char.txt
jaidedread/character/pl_char.txt
jaidedread/character/pt_char.txt
jaidedread/character/ro_char.txt
jaidedread/character/sk_char.txt
jaidedread/character/sl_char.txt
jaidedread/character/sq_char.txt
jaidedread/character/sv_char.txt
jaidedread/character/sw_char.txt
jaidedread/character/th_char.txt
jaidedread/character/tl_char.txt
jaidedread/character/tr_char.txt
jaidedread/character/uz_char.txt
jaidedread/character/vi_char.txt
jaidedread/dict/af.txt
jaidedread/dict/az.txt
jaidedread/dict/bs.txt
jaidedread/dict/cs.txt
jaidedread/dict/cy.txt
jaidedread/dict/da.txt
jaidedread/dict/de.txt
jaidedread/dict/en.txt
jaidedread/dict/es.txt
jaidedread/dict/et.txt
jaidedread/dict/fr.txt
jaidedread/dict/ga.txt
jaidedread/dict/hr.txt
jaidedread/dict/hu.txt
jaidedread/dict/id.txt
jaidedread/dict/is.txt
jaidedread/dict/it.txt
jaidedread/dict/ku.txt
jaidedread/dict/la.txt
