Metadata-Version: 1.1
Name: jaidedread
Version: 0.9
Summary: End-to-End Multi-Lingual Optical Character Recognition (OCR) Solution
Home-page: https://github.com/jaided/jaidedread
Author: Rakpong Kittinaradorn
Author-email: r.kittinaradorn@gmail.com
License: Apache License 2.0
Download-URL: https://github.com/jaided/jaidedread.git
Keywords: ocr optical character recognition deep learning neural network
Platform: UNKNOWN
Classifier: Development Status :: 4 - Beta
